bert_pruners/__init__.py
bert_pruners/bert_pruner.py
bert_pruners/factory.py
bert_pruners/factory_est.py
bert_pruners/main.py
bert_pruners-0.0.6.dist-info/METADATA
bert_pruners-0.0.6.dist-info/WHEEL
bert_pruners-0.0.6.dist-info/entry_points.txt
bert_pruners-0.0.6.dist-info/top_level.txt
bert_pruners-0.0.6.dist-info/RECORD
